<?xml version="1.0" encoding="utf-8"?>
<!--
  SPDX-FileCopyrightText: TheParasiteProject
  SPDX-License-Identifier: GPL-3.0-or-later
  License-Filename: LICENSE
-->
<permissions>
    <privapp-permissions package="com.android.bluetooth.bthelper">
        <permission name="android.permission.ACCESS_BACKGROUND_LOCATION" />
        <permission name="android.permission.ACCESS_COARSE_LOCATION" />
        <permission name="android.permission.ACCESS_FINE_LOCATION"/>
        <permission name="android.permission.BATTERY_STATS"/>
        <permission name="android.permission.BLUETOOTH" />
        <permission name="android.permission.BLUETOOTH_ADMIN" />
        <permission name="android.permission.BLUETOOTH_ADVERTISE" />
        <permission name="android.permission.BLUETOOTH_CONNECT" />
        <permission name="android.permission.BLUETOOTH_PRIVILEGED" />
        <permission name="android.permission.BLUETOOTH_SCAN" />
        <permission name="android.permission.INTERACT_ACROSS_USERS" />
        <permission name="android.permission.INTERACT_ACROSS_USERS_FULL" />
        <permission name="android.permission.MEDIA_CONTENT_CONTROL" />
        <permission name="android.permission.RECEIVE_BOOT_COMPLETED" />
        <permission name="android.permission.UPDATE_DEVICE_STATS" />
    </privapp-permissions>
</permissions>
